llm_lab/__init__.py
llm_lab/analysis.py
llm_lab/config.py
llm_lab/experiment.py
llm_lab/metrics.py
llm_lab/model_client.py
llm_lab/storage.py
llm_lab/utils.py
llm_lab-0.1.0.dist-info/licenses/LICENSE
llm_lab-0.1.0.dist-info/METADATA
llm_lab-0.1.0.dist-info/WHEEL
llm_lab-0.1.0.dist-info/top_level.txt
llm_lab-0.1.0.dist-info/RECORD
