Metadata-Version: 2.4
Name: llm-lab
Version: 0.1.0
Summary: A minimal, notebook-first framework for running reproducible LLM experiments and comparing multiple models over JSONL/CSV datasets.
Author: Sayan Sahay
License: MIT
Project-URL: Homepage, https://github.com/Sayan-11/llm-lab
Project-URL: Source, https://github.com/Sayan-11/llm-lab
Project-URL: Issues, https://github.com/Sayan-11/llm-lab/issues
Requires-Python: >=3.9
License-File: LICENSE
Requires-Dist: openai>=1.0.0
Requires-Dist: jsonlines>=4.0.0
Requires-Dist: pandas>=1.5.0
Requires-Dist: matplotlib>=3.5.0
Requires-Dist: ipython>=8.0.0
Dynamic: license-file
